<?xml version="1.0" encoding="utf-8" standalone="yes"?>
<!DOCTYPE ROOT PUBLIC "" ""[]>
<Project_Model xmlns:r="reflection" r:Version="2">
  <AudioAnalysisData Key="307d58c9-9cd4-4e02-b72e-6e7421d6a781">
    <AudioAnalysisSettings>
      <Item AnalizeMono="False" AudioMean="0" Autogain="False" DbRange="96" Enable="True" GainBeat="1, 1, 1, 1" GainFFT4="1, 1, 1, 1" Key="77009df2-fa8f-4ea7-850f-8cf0fc646424" MainGain="1" Max="0" Min="0" MinVelocity="0" PickFreq1="41" PickFreq2="265" PickFreq3="600" PickFreq4="11000" PickWidth="8" Pow="4" Resolution="1024" Smooth="0">
        <AudioSource>
          <Item AudioChannels="0, 1" Source="" />
        </AudioSource>
      </Item>
    </AudioAnalysisSettings>
  </AudioAnalysisData>
  <DriverSettings DeviceName="WASAPI: Current System Device" Enable="True" EnableInput="False" InputChannels="2" InputOffset="0" OutputChannels="2" OutputOffset="0" SampleRate="48000" SpatialAudio="False" WasapiInput="Default" />
  <Multitrack Duration="240">
    <TimelinerControls BaseFPS="60" BPM="120" FPS="60" InputVolume="1" LoopEnable="True" LoopFrom="0" LoopMode="True" LoopTo="240" PPQN="384" Volume="1" />
    <Tracks />
  </Multitrack>
  <OSCNetwork Enable="False">
    <IPs>
      <Item IP="127.0.0.1" Key="fc1d92d5-1bdf-40a6-b4c3-de37477949a5" Name="Local" Port="9999" Send="True" />
    </IPs>
  </OSCNetwork>
  <SpatialAudio>
    <Sources>
      <Item AudioChannels="0, 1" Source="" />
    </Sources>
    <Speakers>
      <Item SourceLevels="1" SpeakerLevel="1" />
      <Item SourceLevels="1" SpeakerLevel="1" />
    </Speakers>
  </SpatialAudio>
  <TargetAppModel Key="b2cafe8c-e249-46fd-9c0c-3a7b2ccdc5d6" r:Type="Luminaria_Model [Luminaria.Model]">
    <AnimationsBank Key="567907c9-1ad8-4672-828b-18df4692fd41">
      <ParametersBank>
        <Item AccumulatorCount="16" AccumulatorFilterTime="0" AudioVelocityMult="1" BangDecay="0.5" BangMode="In" BangTransition="Linear" GlobalGain="1" Key="392ef3be-254b-4ac1-9fe7-27a95259f14e" MapMode="Clamp" Mirror="False" Name="" Offset="0" Pause="False" RangeIn="0, 1" RangeOut="0, 1" Reset="False" Reverse="False" Seed="0" VelocityMult="1">
          <Parameters>
            <Item AccumulatorMapMode="Off" AdditionMode="Add" AnimationCount="500" AnimationMode="Peak" AudioBuffer="False" AudioPhaseGain="1" AudioSourcePhase="Off" DefaultValue="0" Enable="True" ExternalIsBPM="False" Factor="1" InternalMExternal="False" Invert="False" Key="66905a1a-3ffd-48b3-879f-65fbaa9119cb" MapMode="Off" Mirror="False" MirrorOffset="0" MirrorPhase="False" Mode="In" Offset="0" Pause="False" PeakCount="500" PeakPhaseMode="Forward" QueueDecay="0" QueueIIR="0" QueueSource="Mean" QueueStatic="False" RangeIn="0, 1" RangeOut="0, 1" RectSlope="0.5" Reset="False" Reverse="False" Smooth="0" Transition="Linear" Velocity="0.15" />
          </Parameters>
        </Item>
      </ParametersBank>
    </AnimationsBank>
    <Lamps_Model Key="5eca2c29-6799-48e7-8421-e6cede87dd09">
      <Lamps>
        <Item Color="1, 1, 1, 1" ColorInfluence="1" Gain="1" GainInfluence="1" Key="a29c0abb-f863-4a22-a0c5-6488576d00ad" Name="" Position="0, 0, 0" Type="0" />
      </Lamps>
    </Lamps_Model>
    <Sources_Model AudioSourcesCount="2" Key="e4f473d8-d285-475d-b168-36d709a2b467">
      <Sources>
        <Item AudioSources="0, 1" ColorBlendMode="Add" Field="All" Gain="1" GainBlendMode="Add" Gradient="1" InfluenceMode="Sphere" InputType="0" Key="16131b7a-8475-45ad-9d28-6a393b7baf99" Name="" Position="0, 0, 0" Rotation="0, 0, 0" Size="1, 1, 1" TweenMode="In" TweenTransition="Linear">
          <Colors>
            <Item>1, 1, 1, 1</Item>
          </Colors>
        </Item>
      </Sources>
    </Sources_Model>
    <Speakers_Model Key="c8c61d69-be61-4c8f-9ae6-7301dada4726">
      <Speakers>
        <Item Gain="1" Key="7582b8b0-8af5-4d5b-a680-03a86eaeb602" Name="" Position="0, 0, 0" />
      </Speakers>
    </Speakers_Model>
  </TargetAppModel>
  <TimelinerSettings AudioAnalysis="False" AudioAnalysisMonitor="False" AudioAnalysisSize="0.4" AudioLevelsEnable="False" BinderEnable="False" BPMEnable="False" HMSFEnable="False" InspectorEnable="False" InspectorSize="4" KeyframeEnable="False" PlayOnStart="False" SpatialAudio="False" TimelinerEnable="True" TrackEnable="False" WaveformsEnable="True" />
</Project_Model>